mkdocs_embed_file_plugins/__init__.py
mkdocs_embed_file_plugins/plugin.py
mkdocs_embed_file_plugins/src/__init__.py
mkdocs_embed_file_plugins/src/links_correction.py
mkdocs_embed_file_plugins/src/search_quote.py
mkdocs_embed_file_plugins/src/utils.py
mkdocs_embed_file_plugins-2.0.10.dist-info/LICENSE
mkdocs_embed_file_plugins-2.0.10.dist-info/METADATA
mkdocs_embed_file_plugins-2.0.10.dist-info/WHEEL
mkdocs_embed_file_plugins-2.0.10.dist-info/entry_points.txt
mkdocs_embed_file_plugins-2.0.10.dist-info/top_level.txt
mkdocs_embed_file_plugins-2.0.10.dist-info/RECORD
