Metadata-Version: 2.1
Name: mkdocs_embed_file_plugins
Version: 2.0.10
Summary: A plugin to quote file from docs
Home-page: https://github.com/ObsidianPublisher/mkdocs-embed_file-plugin
Author: Mara-Li
Author-email: mara-li@icloud.com
License: AGPL
Keywords: obsidian,obsidian.md,mkdocs,file,embed,cite,quote
Classifier: Natural Language :: English
Classifier: Natural Language :: French
Classifier: Topic :: Text Processing :: Markup :: Markdown
Classifier: License :: OSI Approved :: GNU Affero General Public License v3 or later (AGPLv3+)
Requires-Python: >=3.7
License-File: LICENSE
Requires-Dist: mkdocs
Requires-Dist: setuptools
Requires-Dist: Markdown
Requires-Dist: beautifulsoup4
Requires-Dist: python-frontmatter
Requires-Dist: mdx-wikilink-plus
Requires-Dist: mkdocs-callouts
Requires-Dist: mkdocs-custom-tags-attributes
Requires-Dist: pymdown-extensions
